compose-stubs/__init__.pyi
compose_stubs-1.0.0.dist-info/LICENSE
compose_stubs-1.0.0.dist-info/METADATA
compose_stubs-1.0.0.dist-info/WHEEL
compose_stubs-1.0.0.dist-info/top_level.txt
compose_stubs-1.0.0.dist-info/RECORD
