Metadata-Version: 2.1
Name: compose-stubs
Version: 1.0.0
Summary: Type stubs for compose
Home-page: https://github.com/mentalisttraceur/python-compose-stubs
Author: Alexander Kozhevnikov
Author-email: mentalisttraceur@gmail.com
License: 0BSD
Classifier: Development Status :: 5 - Production/Stable
Classifier: Programming Language :: Python :: 3
Classifier: Operating System :: OS Independent
License-File: LICENSE
